{
    "meta": {
        "title": "E-Commerce og Detaljhandel Programvareutvikling | Intellectsoft Norge",
        "description": "E-commerce og detaljhandel: lojalitets apps, kunde skjermer og andre løsninger som tar handleopplevelsen til et nytt nivå ved Intellectsoft",
        "keywords": "ecommerce programvareutvikling, detaljhandel programvareutvikling, lojalitets apps, kunde skjermer, andre løsninger, programvareutvikling selskap, intellectsoft Norge, Intellectsoft No, intellectsoft oslo"
    },
    "title": "Ecommerce",
    "region": "NO",
    "about": {
        "phone_1": "+1 (650) 300 4335",
        "phone_2": "+1 (855) TOP DEVS",
        "country_1": "Norway",
        "address_1": "Bogstadveien 27B, 0355 Oslo",
        "country_2": "FINLAND",
        "address_2": "Forum Lasikulma, 6.krs\nMannerheimintie 20B\nHelsinki 00100"
    }
}